[{
    "Company Name": "Collier, Mayert and Bahringer"
    "Description": "Total 24/7 Matrices"
    "Tagline": "Repurpose Real-Time Webservices"
    "Company Email": "csipes@waters.com"
    "Ein": "75-7734445"
}, {
    "Company Name": "Prohaska"
    "Description": "Triple-Buffered Motivating Infrastructure"
    "Tagline": "Aggregate Proactive Vortals"
    "Company Email": "robel.kenna@dare.com"
    "Ein": "86-3641996"
}, {
    "Company Name": "Dickens Ltd"
    "Description": "Synergistic Local Capability"
    "Tagline": "Productize Open-Source Technologies"
    "Company Email": "nya.erdman@fisher.com"
    "Ein": "77-3440394"
}, {
    "Company Name": "Ziemann-Fritsch"
    "Description": "Extended Uniform Hardware"
    "Tagline": "Optimize User-Centric Experiences"
    "Company Email": "florencio.swaniawski@torphy.com"
    "Ein": "31-1262744"
}, {
    "Company Name": "Murphy, Champlin and Spinka"
    "Description": "Intuitive Context-Sensitive Internetsolution"
    "Tagline": "Synergize Turn-Key Networks"
    "Company Email": "johnny68@hills.net"
    "Ein": "53-3644500"
}, {
    "Company Name": "Stanton LLC"
    "Description": "Robust Composite Paradigm"
    "Tagline": "Harness Customized Webservices"
    "Company Email": "marcia13@bartoletti.org"
    "Ein": "40-8482267"
}, {
    "Company Name": "Torphy-Bogan"
    "Description": "Profound Bandwidth-Monitored Monitoring"
    "Tagline": "Incubate Distributed Content"
    "Company Email": "cormier.carolyn@miller.com"
    "Ein": "84-7569823"
}, {
    "Company Name": "Gleason, Wisozk and Renner"
    "Description": "Cross-Platform Incremental Monitoring"
    "Tagline": "Embrace Rich Niches"
    "Company Email": "julian69@harris.net"
    "Ein": "47-1441362"
}, {
    "Company Name": "Bednar, Gulgowski and Davis"
    "Description": "Upgradable Interactive Solution"
    "Tagline": "Recontextualize Integrated Mindshare"
    "Company Email": "lexie.bogan@langworth.info"
    "Ein": "74-2160070"
}, {
    "Company Name": "Spinka PLC"
    "Description": "Inverse Scalable Parallelism"
    "Tagline": "Synergize User-Centric Functionalities"
    "Company Email": "fhowell@towne.com"
    "Ein": "72-7875575"
}, {
    "Company Name": "Lesch Inc"
    "Description": "Multi-Layered Motivating Database"
    "Tagline": "Visualize Revolutionary Initiatives"
    "Company Email": "hessel.oscar@heathcote.org"
    "Ein": "38-5449207"
}, {
    "Company Name": "Turner Group"
    "Description": "Pre-Emptive Even-Keeled Graphicaluserinterface"
    "Tagline": "Harness Viral Applications"
    "Company Email": "vgulgowski@reichert.info"
    "Ein": "80-6640823"
}, {
    "Company Name": "Schoen-Daugherty"
    "Description": "Team-Oriented Upward-Trending Installation"
    "Tagline": "Drive Customized Content"
    "Company Email": "iliana02@kertzmann.com"
    "Ein": "36-9963455"
}, {
    "Company Name": "Parker, Marvin and Sauer"
    "Description": "Optimized Zeroadministration Moratorium"
    "Tagline": "Drive Front-End Convergence"
    "Company Email": "lang.emely@dibbert.com"
    "Ein": "64-8488459"
}, {
    "Company Name": "Prohaska-Berge"
    "Description": "Open-Source Contextually-Based Standardization"
    "Tagline": "Syndicate Granular Users"
    "Company Email": "ashley95@hegmann.com"
    "Ein": "82-9843937"
}, {
    "Company Name": "Rogahn-Daniel"
    "Description": "Self-Enabling Contextually-Based Encoding"
    "Tagline": "Innovate E-Business Synergies"
    "Company Email": "zkemmer@moore.com"
    "Ein": "99-3422644"
}, {
    "Company Name": "Borer-Stamm"
    "Description": "Horizontal 5Thgeneration Success"
    "Tagline": "Whiteboard Front-End Action-Items"
    "Company Email": "jlind@kiehn.info"
    "Ein": "12-5903621"
}, {
    "Company Name": "Blick-Nolan"
    "Description": "Enhanced Web-Enabled Conglomeration"
    "Tagline": "Evolve 24/7 Technologies"
    "Company Email": "weimann.maxwell@walker.net"
    "Ein": "64-1170094"
}, {
    "Company Name": "Baumbach-Boehm"
    "Description": "Organic Discrete Database"
    "Tagline": "Incentivize Clicks-And-Mortar Channels"
    "Company Email": "prunolfsdottir@rutherford.com"
    "Ein": "94-1309617"
}, {
    "Company Name": "Bednar, Boyer and Krajcik"
    "Description": "Horizontal 4Thgeneration Utilisation"
    "Tagline": "Reintermediate Collaborative Web-Readiness"
    "Company Email": "kathryne.hayes@halvorson.com"
    "Ein": "84-2534250"
}]